TigGUI/AboutDialog.py
TigGUI/MainWindow.py
TigGUI/SkyModelTreeWidget.py
TigGUI/Widgets.py
TigGUI/__init__.py
TigGUI/init.py
TigGUI/tigger.conf
TigGUI/Images/Colormaps.py
TigGUI/Images/ControlDialog.py
TigGUI/Images/Controller.py
TigGUI/Images/FITSHeaders.py
TigGUI/Images/Manager.py
TigGUI/Images/RenderControl.py
TigGUI/Images/SkyImage.py
TigGUI/Images/__init__.py
TigGUI/Images/ColormapTables/Karma.py
TigGUI/Images/ColormapTables/__init__.py
TigGUI/Plot/MouseModes.py
TigGUI/Plot/SkyModelPlot.py
TigGUI/Plot/__init__.py
TigGUI/Tools/__init__.py
TigGUI/Tools/add_brick.py
TigGUI/Tools/dependency_check.py
TigGUI/Tools/export_karma.py
TigGUI/Tools/make_brick.py
TigGUI/Tools/restore_image.py
TigGUI/Tools/source_selector.py
TigGUI/icons/astron_logo.png
TigGUI/icons/big_minus.png
TigGUI/icons/big_plus.png
TigGUI/icons/center_image.png
TigGUI/icons/colours.png
TigGUI/icons/full_range.png
TigGUI/icons/intensity_graph.png
TigGUI/icons/locked.png
TigGUI/icons/raise_up.png
TigGUI/icons/ruler.png
TigGUI/icons/subset_range.png
TigGUI/icons/tigger_logo.png
TigGUI/icons/tigger_splash.png
TigGUI/icons/tigger_starface.png
TigGUI/icons/unlocked.png
TigGUI/icons/window_larger.png
TigGUI/icons/window_sigma.png
TigGUI/icons/window_smaller.png
TigGUI/icons/wizard.png
TigGUI/icons/zoom-out.png
TigGUI/icons/zoom_colours.png
TigGUI/icons/zoom_in.png
TigGUI/icons/zoom_out.png
TigGUI/icons/zoom_range.png
TigGUI/kitties/__init__.py
TigGUI/kitties/config.py
TigGUI/kitties/pixmaps.py
TigGUI/kitties/utils.py
TigGUI/kitties/widgets.py
TigGUI/version_info/__init__.py
astro_tigger-1.6.1.1.data/scripts/tigger
home/runner/.local/share/applications/tigger.desktop
home/runner/.local/share/icons/tigger_logo.png
astro_tigger-1.6.1.1.dist-info/METADATA
astro_tigger-1.6.1.1.dist-info/WHEEL
astro_tigger-1.6.1.1.dist-info/top_level.txt
astro_tigger-1.6.1.1.dist-info/RECORD
