Metadata-Version: 2.1
Name: astro-tigger
Version: 1.6.1.1
Summary: yet another FITS image viewer
Home-page: https://github.com/ratt-ru/tigger
Author: Oleg Smirnov
Author-email: osmirnov@gmail.com
License: UNKNOWN
Platform: UNKNOWN
Requires-Python: >=3.6
Requires-Dist: numpy
Requires-Dist: scipy
Requires-Dist: astlib
Requires-Dist: astropy
Requires-Dist: astro-tigger-lsm (==1.7.1)
Requires-Dist: configparser
